COPYING.txt
COPYRIGHT.txt
ChangeLog.txt
ClientForm.py
GeneralFAQ.html
INSTALL.txt
MANIFEST.in
README.html
README.html.in
README.txt
ez_setup.py
setup.cfg
setup.py
test.py
ClientForm.egg-info/PKG-INFO
ClientForm.egg-info/SOURCES.txt
ClientForm.egg-info/dependency_links.txt
ClientForm.egg-info/top_level.txt
ClientForm.egg-info/zip-safe
examples/data.dat
examples/data.txt
examples/echo.cgi
examples/example.html
examples/example.py
examples/simple.py
testdata/Auth.html
testdata/FullSearch.html
testdata/GeneralSearch.html
testdata/MarkedRecords.html
testdata/MarkedResults.html
testdata/Results.html
testdata/SearchType.html
